Workbook

Sheet Instrucciones
A1: Libro de seguimiento · UEA 2211088 Informática · Trimestre 26-O
A3: Propósito | B3: Registrar cada actividad del trimestre para tres fines simultáneos: retroalimentar al alumno, calcular la calificación conforme al programa oficial, y evaluar si el método de aprendizaje basado en proyectos funcionó.
A5: CÓMO SE USA
A6: 1. Alumnos | B6: Vuelca aquí la lista del grupo y los resultados del CHAEA y del diagnóstico levantados la semana del 17 al 20 de septiembre. Los niveles y el estilo dominante se calculan solos.
A7: 2. Asistencia | B7: Se llena cada sesión, en el momento. Usa A (asistió), F (falta) o J (justificada).
A8: 3. Entregables | B8: Una fila por equipo y proyecto. Se capturan los seis criterios de la rúbrica, de 0 a 3.
A9: 4. Bitácora IA | B9: Una calificación de 0 a 10 por alumno y proyecto, sobre la calidad de la interrogación al chatbot, no sobre la cantidad de uso.
A10: 5. Exámenes | B10: Los tres exámenes escritos, de 0 a 100.
A11: 6. Calificaciones | B11: No se toca: calcula todo. Es la hoja que se usa para el acta.
A12: 7. Riesgo | B12: No se toca: semáforo de deserción. Revísala cada lunes, cinco minutos.
A13: 8. Diario docente | B13: Se llena al terminar cada sesión, en cinco minutos. Es la materia prima de la evaluación del método y de cualquier publicación posterior.
A14: 9. Evaluación del método | B14: Se llena al cierre del trimestre, con los datos que las hojas anteriores ya reunieron.
A16: CÓDIGO DE COLOR
A17: Azul | B17: Celda que tú capturas.
A18: Negro | B18: Fórmula. No la sobrescribas.
A19: Fondo amarillo | B19: Parámetro que puedes ajustar (ponderaciones, umbrales).
A20: Gris cursiva | B20: Fila de ejemplo. Bórrala antes de usar el libro.
A22: PONDERACIONES | B22: Están en la hoja Calificaciones, celdas con fondo amarillo. Suman 100% y cumplen el programa oficial: 70% en evaluaciones periódicas escritas, 30% en el resto.
A23: ADVERTENCIA | B23: Este libro no sustituye el acta oficial. Es un instrumento de trabajo del profesor.

Sheet Baremo
A1: Baremo general del CHAEA (Alonso, Gallego y Honey, 1994)
A3: Estilo | B3: Muy baja (10%) | C3: Baja (20%) | D3: Moderada (40%) | E3: Alta (20%) | F3: Muy alta (10%)
A4: Activo | B4: 0 – 6 | C4: 7 – 8 | D4: 9 – 12 | E4: 13 – 14 | F4: 15 – 20
A5: Reflexivo | B5: 0 – 10 | C5: 11 – 13 | D5: 14 – 17 | E5: 18 – 19 | F5: 20
A6: Teórico | B6: 0 – 6 | C6: 7 – 9 | D6: 10 – 13 | E6: 14 – 15 | F6: 16 – 20
A7: Pragmático | B7: 0 – 8 | C7: 9 – 10 | D7: 11 – 13 | E7: 14 – 15 | F7: 16 – 20
A9: Las cuatro escalas NO son comparables en bruto: un 14 en reflexivo no equivale a un 14 en activo. El baremo convierte la puntuación a un nivel de preferencia relativo a la población normativa (muestra de 1,371 personas). El estilo dominante es aquel donde se alcanza el nivel más alto, no la puntuación bruta mayor.
A12: Estilo | B12: Nivel 2 desde | C12: Nivel 3 desde | D12: Nivel 4 desde | E12: Nivel 5 desde | F12: Etiqueta
A13: Activo | B13: 7 | C13: 9 | D13: 13 | E13: 15
A14: Reflexivo | B14: 11 | C14: 14 | D14: 18 | E14: 20
A15: Teórico | B15: 7 | C15: 10 | D15: 14 | E15: 16
A16: Pragmático | B16: 9 | C16: 11 | D16: 14 | E16: 16
A17: Tabla auxiliar para las fórmulas de la hoja Alumnos. No modificar.
A18: Etiquetas: | B18: Activo | C18: Reflexivo | D18: Teórico | E18: Pragmático

Sheet Alumnos
A1: Alumnos · perfil de entrada
A3: # | B3: Nombre completo | C3: Correo | D3: Equipo | E3: Rol P1 | F3: Rol P2 | G3: Rol P3 | H3: CHAEA Activo | I3: CHAEA Reflex. | J3: CHAEA Teórico | K3: CHAEA Pragm. | L3: Niv A | M3: Niv R | N3: Niv T | O3: Niv P | P3: Estilo dominante | Q3: Diagnóstico (0-17) | R3: Punto de partida | S3: ¿Contestó pre-curso?
A4: 1 | B4: EJEMPLO — borrar esta fila | C4: ejemplo@xanum.uam.mx | D4: E1 | E4: Explorador | F4: Cronista | G4: Arquitecto | H4: 11 | I4: 15 | J4: 9 | K4: 13 | L4: =IF(H4="","",IF(H4>=Baremo!$E$13,5,IF(H4>=Baremo!$D$13,4,IF(H4>=Baremo!$C$13,3,IF(H4>=Baremo!$B$13,2,1))))) -> 3 | M4: =IF(I4="","",IF(I4>=Baremo!$E$14,5,IF(I4>=Baremo!$D$14,4,IF(I4>=Baremo!$C$14,3,IF(I4>=Baremo!$B$14,2,1))))) -> 3 | N4: =IF(J4="","",IF(J4>=Baremo!$E$15,5,IF(J4>=Baremo!$D$15,4,IF(J4>=Baremo!$C$15,3,IF(J4>=Baremo!$B$15,2,1))))) -> 2 | O4: =IF(K4="","",IF(K4>=Baremo!$E$16,5,IF(K4>=Baremo!$D$16,4,IF(K4>=Baremo!$C$16,3,IF(K4>=Baremo!$B$16,2,1))))) -> 3 | P4: =IFERROR(INDEX(Baremo!$B$18:$E$18,MATCH(MAX(L4:O4),L4:O4,0)),"") -> Activo | Q4: 9 | R4: =IF(Q4="","",IF(Q4<=6,"Elemental",IF(Q4<=10,"Funcional",IF(Q4<=14,"Sólido","Avanzado")))) -> Funcional | S4: Sí
A5: 1 | L5: =IF(H5="","",IF(H5>=Baremo!$E$13,5,IF(H5>=Baremo!$D$13,4,IF(H5>=Baremo!$C$13,3,IF(H5>=Baremo!$B$13,2,1))))) | M5: =IF(I5="","",IF(I5>=Baremo!$E$14,5,IF(I5>=Baremo!$D$14,4,IF(I5>=Baremo!$C$14,3,IF(I5>=Baremo!$B$14,2,1))))) | N5: =IF(J5="","",IF(J5>=Baremo!$E$15,5,IF(J5>=Baremo!$D$15,4,IF(J5>=Baremo!$C$15,3,IF(J5>=Baremo!$B$15,2,1))))) | O5: =IF(K5="","",IF(K5>=Baremo!$E$16,5,IF(K5>=Baremo!$D$16,4,IF(K5>=Baremo!$C$16,3,IF(K5>=Baremo!$B$16,2,1))))) | P5: =IFERROR(INDEX(Baremo!$B$18:$E$18,MATCH(MAX(L5:O5),L5:O5,0)),"") | R5: =IF(Q5="","",IF(Q5<=6,"Elemental",IF(Q5<=10,"Funcional",IF(Q5<=14,"Sólido","Avanzado"))))
A6: 2 | L6: =IF(H6="","",IF(H6>=Baremo!$E$13,5,IF(H6>=Baremo!$D$13,4,IF(H6>=Baremo!$C$13,3,IF(H6>=Baremo!$B$13,2,1))))) | M6: =IF(I6="","",IF(I6>=Baremo!$E$14,5,IF(I6>=Baremo!$D$14,4,IF(I6>=Baremo!$C$14,3,IF(I6>=Baremo!$B$14,2,1))))) | N6: =IF(J6="","",IF(J6>=Baremo!$E$15,5,IF(J6>=Baremo!$D$15,4,IF(J6>=Baremo!$C$15,3,IF(J6>=Baremo!$B$15,2,1))))) | O6: =IF(K6="","",IF(K6>=Baremo!$E$16,5,IF(K6>=Baremo!$D$16,4,IF(K6>=Baremo!$C$16,3,IF(K6>=Baremo!$B$16,2,1))))) | P6: =IFERROR(INDEX(Baremo!$B$18:$E$18,MATCH(MAX(L6:O6),L6:O6,0)),"") | R6: =IF(Q6="","",IF(Q6<=6,"Elemental",IF(Q6<=10,"Funcional",IF(Q6<=14,"Sólido","Avanzado"))))
A7: 3 | L7: =IF(H7="","",IF(H7>=Baremo!$E$13,5,IF(H7>=Baremo!$D$13,4,IF(H7>=Baremo!$C$13,3,IF(H7>=Baremo!$B$13,2,1))))) | M7: =IF(I7="","",IF(I7>=Baremo!$E$14,5,IF(I7>=Baremo!$D$14,4,IF(I7>=Baremo!$C$14,3,IF(I7>=Baremo!$B$14,2,1))))) | N7: =IF(J7="","",IF(J7>=Baremo!$E$15,5,IF(J7>=Baremo!$D$15,4,IF(J7>=Baremo!$C$15,3,IF(J7>=Baremo!$B$15,2,1))))) | O7: =IF(K7="","",IF(K7>=Baremo!$E$16,5,IF(K7>=Baremo!$D$16,4,IF(K7>=Baremo!$C$16,3,IF(K7>=Baremo!$B$16,2,1))))) | P7: =IFERROR(INDEX(Baremo!$B$18:$E$18,MATCH(MAX(L7:O7),L7:O7,0)),"") | R7: =IF(Q7="","",IF(Q7<=6,"Elemental",IF(Q7<=10,"Funcional",IF(Q7<=14,"Sólido","Avanzado"))))
A8: 4 | L8: =IF(H8="","",IF(H8>=Baremo!$E$13,5,IF(H8>=Baremo!$D$13,4,IF(H8>=Baremo!$C$13,3,IF(H8>=Baremo!$B$13,2,1))))) | M8: =IF(I8="","",IF(I8>=Baremo!$E$14,5,IF(I8>=Baremo!$D$14,4,IF(I8>=Baremo!$C$14,3,IF(I8>=Baremo!$B$14,2,1))))) | N8: =IF(J8="","",IF(J8>=Baremo!$E$15,5,IF(J8>=Baremo!$D$15,4,IF(J8>=Baremo!$C$15,3,IF(J8>=Baremo!$B$15,2,1))))) | O8: =IF(K8="","",IF(K8>=Baremo!$E$16,5,IF(K8>=Baremo!$D$16,4,IF(K8>=Baremo!$C$16,3,IF(K8>=Baremo!$B$16,2,1))))) | P8: =IFERROR(INDEX(Baremo!$B$18:$E$18,MATCH(MAX(L8:O8),L8:O8,0)),"") | R8: =IF(Q8="","",IF(Q8<=6,"Elemental",IF(Q8<=10,"Funcional",IF(Q8<=14,"Sólido","Avanzado"))))
A9: 5 | L9: =IF(H9="","",IF(H9>=Baremo!$E$13,5,IF(H9>=Baremo!$D$13,4,IF(H9>=Baremo!$C$13,3,IF(H9>=Baremo!$B$13,2,1))))) | M9: =IF(I9="","",IF(I9>=Baremo!$E$14,5,IF(I9>=Baremo!$D$14,4,IF(I9>=Baremo!$C$14,3,IF(I9>=Baremo!$B$14,2,1))))) | N9: =IF(J9="","",IF(J9>=Baremo!$E$15,5,IF(J9>=Baremo!$D$15,4,IF(J9>=Baremo!$C$15,3,IF(J9>=Baremo!$B$15,2,1))))) | O9: =IF(K9="","",IF(K9>=Baremo!$E$16,5,IF(K9>=Baremo!$D$16,4,IF(K9>=Baremo!$C$16,3,IF(K9>=Baremo!$B$16,2,1))))) | P9: =IFERROR(INDEX(Baremo!$B$18:$E$18,MATCH(MAX(L9:O9),L9:O9,0)),"") | R9: =IF(Q9="","",IF(Q9<=6,"Elemental",IF(Q9<=10,"Funcional",IF(Q9<=14,"Sólido","Avanzado"))))
A10: 6 | L10: =IF(H10="","",IF(H10>=Baremo!$E$13,5,IF(H10>=Baremo!$D$13,4,IF(H10>=Baremo!$C$13,3,IF(H10>=Baremo!$B$13,2,1))))) | M10: =IF(I10="","",IF(I10>=Baremo!$E$14,5,IF(I10>=Baremo!$D$14,4,IF(I10>=Baremo!$C$14,3,IF(I10>=Baremo!$B$14,2,1))))) | N10: =IF(J10="","",IF(J10>=Baremo!$E$15,5,IF(J10>=Baremo!$D$15,4,IF(J10>=Baremo!$C$15,3,IF(J10>=Baremo!$B$15,2,1))))) | O10: =IF(K10="","",IF(K10>=Baremo!$E$16,5,IF(K10>=Baremo!$D$16,4,IF(K10>=Baremo!$C$16,3,IF(K10>=Baremo!$B$16,2,1))))) | P10: =IFERROR(INDEX(Baremo!$B$18:$E$18,MATCH(MAX(L10:O10),L10:O10,0)),"") | R10: =IF(Q10="","",IF(Q10<=6,"Elemental",IF(Q10<=10,"Funcional",IF(Q10<=14,"Sólido","Avanzado"))))
A11: 7 | L11: =IF(H11="","",IF(H11>=Baremo!$E$13,5,IF(H11>=Baremo!$D$13,4,IF(H11>=Baremo!$C$13,3,IF(H11>=Baremo!$B$13,2,1))))) | M11: =IF(I11="","",IF(I11>=Baremo!$E$14,5,IF(I11>=Baremo!$D$14,4,IF(I11>=Baremo!$C$14,3,IF(I11>=Baremo!$B$14,2,1))))) | N11: =IF(J11="","",IF(J11>=Baremo!$E$15,5,IF(J11>=Baremo!$D$15,4,IF(J11>=Baremo!$C$15,3,IF(J11>=Baremo!$B$15,2,1))))) | O11: =IF(K11="","",IF(K11>=Baremo!$E$16,5,IF(K11>=Baremo!$D$16,4,IF(K11>=Baremo!$C$16,3,IF(K11>=Baremo!$B$16,2,1))))) | P11: =IFERROR(INDEX(Baremo!$B$18:$E$18,MATCH(MAX(L11:O11),L11:O11,0)),"") | R11: =IF(Q11="","",IF(Q11<=6,"Elemental",IF(Q11<=10,"Funcional",IF(Q11<=14,"Sólido","Avanzado"))))
A12: 8 | L12: =IF(H12="","",IF(H12>=Baremo!$E$13,5,IF(H12>=Baremo!$D$13,4,IF(H12>=Baremo!$C$13,3,IF(H12>=Baremo!$B$13,2,1))))) | M12: =IF(I12="","",IF(I12>=Baremo!$E$14,5,IF(I12>=Baremo!$D$14,4,IF(I12>=Baremo!$C$14,3,IF(I12>=Baremo!$B$14,2,1))))) | N12: =IF(J12="","",IF(J12>=Baremo!$E$15,5,IF(J12>=Baremo!$D$15,4,IF(J12>=Baremo!$C$15,3,IF(J12>=Baremo!$B$15,2,1))))) | O12: =IF(K12="","",IF(K12>=Baremo!$E$16,5,IF(K12>=Baremo!$D$16,4,IF(K12>=Baremo!$C$16,3,IF(K12>=Baremo!$B$16,2,1))))) | P12: =IFERROR(INDEX(Baremo!$B$18:$E$18,MATCH(MAX(L12:O12),L12:O12,0)),"") | R12: =IF(Q12="","",IF(Q12<=6,"Elemental",IF(Q12<=10,"Funcional",IF(Q12<=14,"Sólido","Avanzado"))))
A13: 9 | L13: =IF(H13="","",IF(H13>=Baremo!$E$13,5,IF(H13>=Baremo!$D$13,4,IF(H13>=Baremo!$C$13,3,IF(H13>=Baremo!$B$13,2,1))))) | M13: =IF(I13="","",IF(I13>=Baremo!$E$14,5,IF(I13>=Baremo!$D$14,4,IF(I13>=Baremo!$C$14,3,IF(I13>=Baremo!$B$14,2,1))))) | N13: =IF(J13="","",IF(J13>=Baremo!$E$15,5,IF(J13>=Baremo!$D$15,4,IF(J13>=Baremo!$C$15,3,IF(J13>=Baremo!$B$15,2,1))))) | O13: =IF(K13="","",IF(K13>=Baremo!$E$16,5,IF(K13>=Baremo!$D$16,4,IF(K13>=Baremo!$C$16,3,IF(K13>=Baremo!$B$16,2,1))))) | P13: =IFERROR(INDEX(Baremo!$B$18:$E$18,MATCH(MAX(L13:O13),L13:O13,0)),"") | R13: =IF(Q13="","",IF(Q13<=6,"Elemental",IF(Q13<=10,"Funcional",IF(Q13<=14,"Sólido","Avanzado"))))
A14: 10 | L14: =IF(H14="","",IF(H14>=Baremo!$E$13,5,IF(H14>=Baremo!$D$13,4,IF(H14>=Baremo!$C$13,3,IF(H14>=Baremo!$B$13,2,1))))) | M14: =IF(I14="","",IF(I14>=Baremo!$E$14,5,IF(I14>=Baremo!$D$14,4,IF(I14>=Baremo!$C$14,3,IF(I14>=Baremo!$B$14,2,1))))) | N14: =IF(J14="","",IF(J14>=Baremo!$E$15,5,IF(J14>=Baremo!$D$15,4,IF(J14>=Baremo!$C$15,3,IF(J14>=Baremo!$B$15,2,1))))) | O14: =IF(K14="","",IF(K14>=Baremo!$E$16,5,IF(K14>=Baremo!$D$16,4,IF(K14>=Baremo!$C$16,3,IF(K14>=Baremo!$B$16,2,1))))) | P14: =IFERROR(INDEX(Baremo!$B$18:$E$18,MATCH(MAX(L14:O14),L14:O14,0)),"") | R14: =IF(Q14="","",IF(Q14<=6,"Elemental",IF(Q14<=10,"Funcional",IF(Q14<=14,"Sólido","Avanzado"))))
A15: 11 | L15: =IF(H15="","",IF(H15>=Baremo!$E$13,5,IF(H15>=Baremo!$D$13,4,IF(H15>=Baremo!$C$13,3,IF(H15>=Baremo!$B$13,2,1))))) | M15: =IF(I15="","",IF(I15>=Baremo!$E$14,5,IF(I15>=Baremo!$D$14,4,IF(I15>=Baremo!$C$14,3,IF(I15>=Baremo!$B$14,2,1))))) | N15: =IF(J15="","",IF(J15>=Baremo!$E$15,5,IF(J15>=Baremo!$D$15,4,IF(J15>=Baremo!$C$15,3,IF(J15>=Baremo!$B$15,2,1))))) | O15: =IF(K15="","",IF(K15>=Baremo!$E$16,5,IF(K15>=Baremo!$D$16,4,IF(K15>=Baremo!$C$16,3,IF(K15>=Baremo!$B$16,2,1))))) | P15: =IFERROR(INDEX(Baremo!$B$18:$E$18,MATCH(MAX(L15:O15),L15:O15,0)),"") | R15: =IF(Q15="","",IF(Q15<=6,"Elemental",IF(Q15<=10,"Funcional",IF(Q15<=14,"Sólido","Avanzado"))))
A16: 12 | L16: =IF(H16="","",IF(H16>=Baremo!$E$13,5,IF(H16>=Baremo!$D$13,4,IF(H16>=Baremo!$C$13,3,IF(H16>=Baremo!$B$13,2,1))))) | M16: =IF(I16="","",IF(I16>=Baremo!$E$14,5,IF(I16>=Baremo!$D$14,4,IF(I16>=Baremo!$C$14,3,IF(I16>=Baremo!$B$14,2,1))))) | N16: =IF(J16="","",IF(J16>=Baremo!$E$15,5,IF(J16>=Baremo!$D$15,4,IF(J16>=Baremo!$C$15,3,IF(J16>=Baremo!$B$15,2,1))))) | O16: =IF(K16="","",IF(K16>=Baremo!$E$16,5,IF(K16>=Baremo!$D$16,4,IF(K16>=Baremo!$C$16,3,IF(K16>=Baremo!$B$16,2,1))))) | P16: =IFERROR(INDEX(Baremo!$B$18:$E$18,MATCH(MAX(L16:O16),L16:O16,0)),"") | R16: =IF(Q16="","",IF(Q16<=6,"Elemental",IF(Q16<=10,"Funcional",IF(Q16<=14,"Sólido","Avanzado"))))
... A29: 25 | L29: =IF(H29="","",IF(H29>=Baremo!$E$13,5,IF(H29>=Baremo!$D$13,4,IF(H29>=Baremo!$C$13,3,IF(H29>=Baremo!$B$13,2,1))))) | M29: =IF(I29="","",IF(I29>=Baremo!$E$14,5,IF(I29>=Baremo!$D$14,4,IF(I29>=Baremo!$C$14,3,IF(I29>=Baremo!$B$14,2,1))))) | N29: =IF(J29="","",IF(J29>=Baremo!$E$15,5,IF(J29>=Baremo!$D$15,4,IF(J29>=Baremo!$C$15,3,IF(J29>=Baremo!$B$15,2,1))))) | O29: =IF(K29="","",IF(K29>=Baremo!$E$16,5,IF(K29>=Baremo!$D$16,4,IF(K29>=Baremo!$C$16,3,IF(K29>=Baremo!$B$16,2,1))))) | P29: =IFERROR(INDEX(Baremo!$B$18:$E$18,MATCH(MAX(L29:O29),L29:O29,0)),"") | R29: =IF(Q29="","",IF(Q29<=6,"Elemental",IF(Q29<=10,"Funcional",IF(Q29<=14,"Sólido","Avanzado"))))

Sheet Asistencia
A1: Asistencia · A = asistió · F = falta · J = justificada
A2: Se llena en el momento, cada sesión. Las columnas de la derecha se calculan solas. | C2: 21-sep | D2: 23-sep | E2: 28-sep | F2: 30-sep | G2: 05-oct | H2: 07-oct | I2: 14-oct | J2: 19-oct | K2: 21-oct | L2: 26-oct | M2: 28-oct | N2: 04-nov | O2: 09-nov | P2: 11-nov | Q2: 16-nov | R2: 18-nov | S2: 23-nov | T2: 25-nov | U2: 30-nov | V2: 02-dic
A3: # | B3: Nombre | C3: S01 | D3: S02 | E3: S03 | F3: S04 | G3: S05 | H3: S06 | I3: S07 | J3: S08 | K3: S09 | L3: S10 | M3: S11 | N3: S12 | O3: S13 | P3: S14 | Q3: S15 | R3: S16 | S3: S17 | T3: S18 | U3: S19 | V3: S20 | W3: Faltas | X3: Justif. | Y3: % asist. | Z3: ¿Derecho a examen?
A4: =IF(Alumnos!A4="","",Alumnos!A4) -> 1 | B4: =IF(Alumnos!B4="","",Alumnos!B4) -> EJEMPLO — borrar esta fila | W4: =COUNTIF(C4:V4,"F") -> 0 | X4: =COUNTIF(C4:V4,"J") -> 0 | Y4: =IFERROR(COUNTIF(C4:V4,"A")/COUNTA(C4:V4),"") | Z4: =IF(Y4="","",IF(Y4>=0.8,"Sí","NO"))
A5: =IF(Alumnos!A5="","",Alumnos!A5) -> 1 | B5: =IF(Alumnos!B5="","",Alumnos!B5) | W5: =COUNTIF(C5:V5,"F") -> 0 | X5: =COUNTIF(C5:V5,"J") -> 0 | Y5: =IFERROR(COUNTIF(C5:V5,"A")/COUNTA(C5:V5),"") | Z5: =IF(Y5="","",IF(Y5>=0.8,"Sí","NO"))
A6: =IF(Alumnos!A6="","",Alumnos!A6) -> 2 | B6: =IF(Alumnos!B6="","",Alumnos!B6) | W6: =COUNTIF(C6:V6,"F") -> 0 | X6: =COUNTIF(C6:V6,"J") -> 0 | Y6: =IFERROR(COUNTIF(C6:V6,"A")/COUNTA(C6:V6),"") | Z6: =IF(Y6="","",IF(Y6>=0.8,"Sí","NO"))
A7: =IF(Alumnos!A7="","",Alumnos!A7) -> 3 | B7: =IF(Alumnos!B7="","",Alumnos!B7) | W7: =COUNTIF(C7:V7,"F") -> 0 | X7: =COUNTIF(C7:V7,"J") -> 0 | Y7: =IFERROR(COUNTIF(C7:V7,"A")/COUNTA(C7:V7),"") | Z7: =IF(Y7="","",IF(Y7>=0.8,"Sí","NO"))
A8: =IF(Alumnos!A8="","",Alumnos!A8) -> 4 | B8: =IF(Alumnos!B8="","",Alumnos!B8) | W8: =COUNTIF(C8:V8,"F") -> 0 | X8: =COUNTIF(C8:V8,"J") -> 0 | Y8: =IFERROR(COUNTIF(C8:V8,"A")/COUNTA(C8:V8),"") | Z8: =IF(Y8="","",IF(Y8>=0.8,"Sí","NO"))
A9: =IF(Alumnos!A9="","",Alumnos!A9) -> 5 | B9: =IF(Alumnos!B9="","",Alumnos!B9) | W9: =COUNTIF(C9:V9,"F") -> 0 | X9: =COUNTIF(C9:V9,"J") -> 0 | Y9: =IFERROR(COUNTIF(C9:V9,"A")/COUNTA(C9:V9),"") | Z9: =IF(Y9="","",IF(Y9>=0.8,"Sí","NO"))
A10: =IF(Alumnos!A10="","",Alumnos!A10) -> 6 | B10: =IF(Alumnos!B10="","",Alumnos!B10) | W10: =COUNTIF(C10:V10,"F") -> 0 | X10: =COUNTIF(C10:V10,"J") -> 0 | Y10: =IFERROR(COUNTIF(C10:V10,"A")/COUNTA(C10:V10),"") | Z10: =IF(Y10="","",IF(Y10>=0.8,"Sí","NO"))
A11: =IF(Alumnos!A11="","",Alumnos!A11) -> 7 | B11: =IF(Alumnos!B11="","",Alumnos!B11) | W11: =COUNTIF(C11:V11,"F") -> 0 | X11: =COUNTIF(C11:V11,"J") -> 0 | Y11: =IFERROR(COUNTIF(C11:V11,"A")/COUNTA(C11:V11),"") | Z11: =IF(Y11="","",IF(Y11>=0.8,"Sí","NO"))
A12: =IF(Alumnos!A12="","",Alumnos!A12) -> 8 | B12: =IF(Alumnos!B12="","",Alumnos!B12) | W12: =COUNTIF(C12:V12,"F") -> 0 | X12: =COUNTIF(C12:V12,"J") -> 0 | Y12: =IFERROR(COUNTIF(C12:V12,"A")/COUNTA(C12:V12),"") | Z12: =IF(Y12="","",IF(Y12>=0.8,"Sí","NO"))
A13: =IF(Alumnos!A13="","",Alumnos!A13) -> 9 | B13: =IF(Alumnos!B13="","",Alumnos!B13) | W13: =COUNTIF(C13:V13,"F") -> 0 | X13: =COUNTIF(C13:V13,"J") -> 0 | Y13: =IFERROR(COUNTIF(C13:V13,"A")/COUNTA(C13:V13),"") | Z13: =IF(Y13="","",IF(Y13>=0.8,"Sí","NO"))
A14: =IF(Alumnos!A14="","",Alumnos!A14) -> 10 | B14: =IF(Alumnos!B14="","",Alumnos!B14) | W14: =COUNTIF(C14:V14,"F") -> 0 | X14: =COUNTIF(C14:V14,"J") -> 0 | Y14: =IFERROR(COUNTIF(C14:V14,"A")/COUNTA(C14:V14),"") | Z14: =IF(Y14="","",IF(Y14>=0.8,"Sí","NO"))
A15: =IF(Alumnos!A15="","",Alumnos!A15) -> 11 | B15: =IF(Alumnos!B15="","",Alumnos!B15) | W15: =COUNTIF(C15:V15,"F") -> 0 | X15: =COUNTIF(C15:V15,"J") -> 0 | Y15: =IFERROR(COUNTIF(C15:V15,"A")/COUNTA(C15:V15),"") | Z15: =IF(Y15="","",IF(Y15>=0.8,"Sí","NO"))
... A29: =IF(Alumnos!A29="","",Alumnos!A29) -> 25 | B29: =IF(Alumnos!B29="","",Alumnos!B29) | W29: =COUNTIF(C29:V29,"F") -> 0 | X29: =COUNTIF(C29:V29,"J") -> 0 | Y29: =IFERROR(COUNTIF(C29:V29,"A")/COUNTA(C29:V29),"") | Z29: =IF(Y29="","",IF(Y29>=0.8,"Sí","NO"))

Sheet Entregables
A1: Entregables de proyecto · rúbrica por equipo (0 a 3 por criterio)
A2: 0 = insuficiente · 1 = suficiente · 2 = bueno · 3 = excelente. Los criterios están en el documento de cada proyecto. El criterio 6 varía por proyecto; ver la rúbrica correspondiente.
A3: Proyecto | B3: Equipo | C3: C1 Evidencia | D3: C2 Modelo/vocabulario | E3: C3 Argumentación | F3: C4 Producto técnico | G3: C5 Bitácora IA | H3: C6 Redacción y roles | I3: Total (18) | J3: % del entregable | K3: Fecha de retroalimentación
A4: P1 | B4: E1 | I4: =IF(COUNT(C4:H4)=0,"",SUM(C4:H4)) | J4: =IF(I4="","",I4/18)
A5: P1 | B5: E2 | I5: =IF(COUNT(C5:H5)=0,"",SUM(C5:H5)) | J5: =IF(I5="","",I5/18)
A6: P1 | B6: E3 | I6: =IF(COUNT(C6:H6)=0,"",SUM(C6:H6)) | J6: =IF(I6="","",I6/18)
A7: P1 | B7: E4 | I7: =IF(COUNT(C7:H7)=0,"",SUM(C7:H7)) | J7: =IF(I7="","",I7/18)
A8: P1 | B8: E5 | I8: =IF(COUNT(C8:H8)=0,"",SUM(C8:H8)) | J8: =IF(I8="","",I8/18)
A10: P2 | B10: E1 | I10: =IF(COUNT(C10:H10)=0,"",SUM(C10:H10)) | J10: =IF(I10="","",I10/18)
A11: P2 | B11: E2 | I11: =IF(COUNT(C11:H11)=0,"",SUM(C11:H11)) | J11: =IF(I11="","",I11/18)
A12: P2 | B12: E3 | I12: =IF(COUNT(C12:H12)=0,"",SUM(C12:H12)) | J12: =IF(I12="","",I12/18)
A13: P2 | B13: E4 | I13: =IF(COUNT(C13:H13)=0,"",SUM(C13:H13)) | J13: =IF(I13="","",I13/18)
A14: P2 | B14: E5 | I14: =IF(COUNT(C14:H14)=0,"",SUM(C14:H14)) | J14: =IF(I14="","",I14/18)
A16: P3 | B16: E1 | I16: =IF(COUNT(C16:H16)=0,"",SUM(C16:H16)) | J16: =IF(I16="","",I16/18)
A17: P3 | B17: E2 | I17: =IF(COUNT(C17:H17)=0,"",SUM(C17:H17)) | J17: =IF(I17="","",I17/18)
... A20: P3 | B20: E5 | I20: =IF(COUNT(C20:H20)=0,"",SUM(C20:H20)) | J20: =IF(I20="","",I20/18)

Sheet Bitacora_IA
A1: Bitácora de uso de IA · calificación individual de 0 a 10 por proyecto
A2: Se califica la CALIDAD de la interrogación, no la cantidad de uso. Una bitácora cuyo campo 'qué corregí o descarté' está siempre vacío documenta delegación y se reprueba.
A3: # | B3: Nombre | C3: P1 (0-10) | D3: P2 (0-10) | E3: P3 (0-10) | F3: Promedio | G3: ¿Cazó el error? | H3: Observaciones
A4: =IF(Alumnos!A4="","",Alumnos!A4) -> 1 | B4: =IF(Alumnos!B4="","",Alumnos!B4) -> EJEMPLO — borrar esta fila | F4: =IF(COUNT(C4:E4)=0,"",AVERAGE(C4:E4))
A5: =IF(Alumnos!A5="","",Alumnos!A5) -> 1 | B5: =IF(Alumnos!B5="","",Alumnos!B5) | F5: =IF(COUNT(C5:E5)=0,"",AVERAGE(C5:E5))
A6: =IF(Alumnos!A6="","",Alumnos!A6) -> 2 | B6: =IF(Alumnos!B6="","",Alumnos!B6) | F6: =IF(COUNT(C6:E6)=0,"",AVERAGE(C6:E6))
A7: =IF(Alumnos!A7="","",Alumnos!A7) -> 3 | B7: =IF(Alumnos!B7="","",Alumnos!B7) | F7: =IF(COUNT(C7:E7)=0,"",AVERAGE(C7:E7))
A8: =IF(Alumnos!A8="","",Alumnos!A8) -> 4 | B8: =IF(Alumnos!B8="","",Alumnos!B8) | F8: =IF(COUNT(C8:E8)=0,"",AVERAGE(C8:E8))
A9: =IF(Alumnos!A9="","",Alumnos!A9) -> 5 | B9: =IF(Alumnos!B9="","",Alumnos!B9) | F9: =IF(COUNT(C9:E9)=0,"",AVERAGE(C9:E9))
A10: =IF(Alumnos!A10="","",Alumnos!A10) -> 6 | B10: =IF(Alumnos!B10="","",Alumnos!B10) | F10: =IF(COUNT(C10:E10)=0,"",AVERAGE(C10:E10))
A11: =IF(Alumnos!A11="","",Alumnos!A11) -> 7 | B11: =IF(Alumnos!B11="","",Alumnos!B11) | F11: =IF(COUNT(C11:E11)=0,"",AVERAGE(C11:E11))
A12: =IF(Alumnos!A12="","",Alumnos!A12) -> 8 | B12: =IF(Alumnos!B12="","",Alumnos!B12) | F12: =IF(COUNT(C12:E12)=0,"",AVERAGE(C12:E12))
A13: =IF(Alumnos!A13="","",Alumnos!A13) -> 9 | B13: =IF(Alumnos!B13="","",Alumnos!B13) | F13: =IF(COUNT(C13:E13)=0,"",AVERAGE(C13:E13))
A14: =IF(Alumnos!A14="","",Alumnos!A14) -> 10 | B14: =IF(Alumnos!B14="","",Alumnos!B14) | F14: =IF(COUNT(C14:E14)=0,"",AVERAGE(C14:E14))
A15: =IF(Alumnos!A15="","",Alumnos!A15) -> 11 | B15: =IF(Alumnos!B15="","",Alumnos!B15) | F15: =IF(COUNT(C15:E15)=0,"",AVERAGE(C15:E15))
... A29: =IF(Alumnos!A29="","",Alumnos!A29) -> 25 | B29: =IF(Alumnos!B29="","",Alumnos!B29) | F29: =IF(COUNT(C29:E29)=0,"",AVERAGE(C29:E29))

Sheet Examenes
A1: Exámenes escritos individuales (0 a 100)
A2: Examen 1: sesión 7 (14-oct) · Examen 2: sesión 12 (04-nov) · Examen 3: semana de evaluaciones globales (7 al 11 de diciembre).
A3: # | B3: Nombre | C3: Examen 1 | D3: Examen 2 | E3: Examen 3 | F3: Promedio simple | G3: Observaciones
A4: =IF(Alumnos!A4="","",Alumnos!A4) -> 1 | B4: =IF(Alumnos!B4="","",Alumnos!B4) -> EJEMPLO — borrar esta fila | F4: =IF(COUNT(C4:E4)=0,"",AVERAGE(C4:E4))
A5: =IF(Alumnos!A5="","",Alumnos!A5) -> 1 | B5: =IF(Alumnos!B5="","",Alumnos!B5) | F5: =IF(COUNT(C5:E5)=0,"",AVERAGE(C5:E5))
A6: =IF(Alumnos!A6="","",Alumnos!A6) -> 2 | B6: =IF(Alumnos!B6="","",Alumnos!B6) | F6: =IF(COUNT(C6:E6)=0,"",AVERAGE(C6:E6))
A7: =IF(Alumnos!A7="","",Alumnos!A7) -> 3 | B7: =IF(Alumnos!B7="","",Alumnos!B7) | F7: =IF(COUNT(C7:E7)=0,"",AVERAGE(C7:E7))
A8: =IF(Alumnos!A8="","",Alumnos!A8) -> 4 | B8: =IF(Alumnos!B8="","",Alumnos!B8) | F8: =IF(COUNT(C8:E8)=0,"",AVERAGE(C8:E8))
A9: =IF(Alumnos!A9="","",Alumnos!A9) -> 5 | B9: =IF(Alumnos!B9="","",Alumnos!B9) | F9: =IF(COUNT(C9:E9)=0,"",AVERAGE(C9:E9))
A10: =IF(Alumnos!A10="","",Alumnos!A10) -> 6 | B10: =IF(Alumnos!B10="","",Alumnos!B10) | F10: =IF(COUNT(C10:E10)=0,"",AVERAGE(C10:E10))
A11: =IF(Alumnos!A11="","",Alumnos!A11) -> 7 | B11: =IF(Alumnos!B11="","",Alumnos!B11) | F11: =IF(COUNT(C11:E11)=0,"",AVERAGE(C11:E11))
A12: =IF(Alumnos!A12="","",Alumnos!A12) -> 8 | B12: =IF(Alumnos!B12="","",Alumnos!B12) | F12: =IF(COUNT(C12:E12)=0,"",AVERAGE(C12:E12))
A13: =IF(Alumnos!A13="","",Alumnos!A13) -> 9 | B13: =IF(Alumnos!B13="","",Alumnos!B13) | F13: =IF(COUNT(C13:E13)=0,"",AVERAGE(C13:E13))
A14: =IF(Alumnos!A14="","",Alumnos!A14) -> 10 | B14: =IF(Alumnos!B14="","",Alumnos!B14) | F14: =IF(COUNT(C14:E14)=0,"",AVERAGE(C14:E14))
A15: =IF(Alumnos!A15="","",Alumnos!A15) -> 11 | B15: =IF(Alumnos!B15="","",Alumnos!B15) | F15: =IF(COUNT(C15:E15)=0,"",AVERAGE(C15:E15))
... A29: =IF(Alumnos!A29="","",Alumnos!A29) -> 25 | B29: =IF(Alumnos!B29="","",Alumnos!B29) | F29: =IF(COUNT(C29:E29)=0,"",AVERAGE(C29:E29))

Sheet Calificaciones
A1: Calificación final · esquema conforme al programa oficial
A2: Hoja calculada. No capturar nada salvo las ponderaciones en amarillo. Los tres exámenes escritos suman 70%, como exige el programa de la UEA.
A4: PONDERACIONES
A5: Examen 1 | B5: 0.23
A6: Examen 2 | B6: 0.23
A7: Examen 3 | B7: 0.24
A8: Entregables de proyecto | B8: 0.15
A9: Bitácora de IA | B9: 0.1
A10: Participación | B10: 0.05
A11: Suma | B11: =SUM(B5:B10) -> 1
A12: Subtotal escrito (debe ser 70%) | B12: =SUM(B5:B7) -> 0.7
A15: # | B15: Nombre | C15: Equipo | D15: Ex1 | E15: Ex2 | F15: Ex3 | G15: Entregables (%) | H15: Bitácora (%) | I15: Participación (%) | J15: Final (0-100) | K15: Final (0-10) | L15: Situación
A16: =IF(Alumnos!A4="","",Alumnos!A4) -> 1 | B16: =IF(Alumnos!B4="","",Alumnos!B4) -> EJEMPLO — borrar esta fila | C16: =IF(Alumnos!D4="","",Alumnos!D4) -> E1 | D16: =IF(Examenes!C4="","",Examenes!C4) | E16: =IF(Examenes!D4="","",Examenes!D4) | F16: =IF(Examenes!E4="","",Examenes!E4) | G16: =IFERROR(SUMIF(Entregables!$B$4:$B$18,$C16,Entregables!$I$4:$I$18)/(COUNTIFS(Entregables!$B$4:$B$18,$C16,Entregables!$I$4:$I$18,">0")*18)*100,"") | H16: =IF(Bitacora_IA!F4="","",Bitacora_IA!F4*10) | I16: =IFERROR(Asistencia!Y4*100,"") | J16: =IFERROR(IF(COUNT(D16:I16)=0,"",D16*$B$5+E16*$B$6+F16*$B$7+G16*$B$8+H16*$B$9+I16*$B$10),"") | K16: =IF(J16="","",ROUND(J16/10,1)) | L16: =IF(K16="","",IF(K16>=9,"MB",IF(K16>=7.8,"B",IF(K16>=6,"S","NA"))))
A17: =IF(Alumnos!A5="","",Alumnos!A5) -> 1 | B17: =IF(Alumnos!B5="","",Alumnos!B5) | C17: =IF(Alumnos!D5="","",Alumnos!D5) | D17: =IF(Examenes!C5="","",Examenes!C5) | E17: =IF(Examenes!D5="","",Examenes!D5) | F17: =IF(Examenes!E5="","",Examenes!E5) | G17: =IFERROR(SUMIF(Entregables!$B$4:$B$18,$C17,Entregables!$I$4:$I$18)/(COUNTIFS(Entregables!$B$4:$B$18,$C17,Entregables!$I$4:$I$18,">0")*18)*100,"") | H17: =IF(Bitacora_IA!F5="","",Bitacora_IA!F5*10) | I17: =IFERROR(Asistencia!Y5*100,"") | J17: =IFERROR(IF(COUNT(D17:I17)=0,"",D17*$B$5+E17*$B$6+F17*$B$7+G17*$B$8+H17*$B$9+I17*$B$10),"") | K17: =IF(J17="","",ROUND(J17/10,1)) | L17: =IF(K17="","",IF(K17>=9,"MB",IF(K17>=7.8,"B",IF(K17>=6,"S","NA"))))
A18: =IF(Alumnos!A6="","",Alumnos!A6) -> 2 | B18: =IF(Alumnos!B6="","",Alumnos!B6) | C18: =IF(Alumnos!D6="","",Alumnos!D6) | D18: =IF(Examenes!C6="","",Examenes!C6) | E18: =IF(Examenes!D6="","",Examenes!D6) | F18: =IF(Examenes!E6="","",Examenes!E6) | G18: =IFERROR(SUMIF(Entregables!$B$4:$B$18,$C18,Entregables!$I$4:$I$18)/(COUNTIFS(Entregables!$B$4:$B$18,$C18,Entregables!$I$4:$I$18,">0")*18)*100,"") | H18: =IF(Bitacora_IA!F6="","",Bitacora_IA!F6*10) | I18: =IFERROR(Asistencia!Y6*100,"") | J18: =IFERROR(IF(COUNT(D18:I18)=0,"",D18*$B$5+E18*$B$6+F18*$B$7+G18*$B$8+H18*$B$9+I18*$B$10),"") | K18: =IF(J18="","",ROUND(J18/10,1)) | L18: =IF(K18="","",IF(K18>=9,"MB",IF(K18>=7.8,"B",IF(K18>=6,"S","NA"))))
A19: =IF(Alumnos!A7="","",Alumnos!A7) -> 3 | B19: =IF(Alumnos!B7="","",Alumnos!B7) | C19: =IF(Alumnos!D7="","",Alumnos!D7) | D19: =IF(Examenes!C7="","",Examenes!C7) | E19: =IF(Examenes!D7="","",Examenes!D7) | F19: =IF(Examenes!E7="","",Examenes!E7) | G19: =IFERROR(SUMIF(Entregables!$B$4:$B$18,$C19,Entregables!$I$4:$I$18)/(COUNTIFS(Entregables!$B$4:$B$18,$C19,Entregables!$I$4:$I$18,">0")*18)*100,"") | H19: =IF(Bitacora_IA!F7="","",Bitacora_IA!F7*10) | I19: =IFERROR(Asistencia!Y7*100,"") | J19: =IFERROR(IF(COUNT(D19:I19)=0,"",D19*$B$5+E19*$B$6+F19*$B$7+G19*$B$8+H19*$B$9+I19*$B$10),"") | K19: =IF(J19="","",ROUND(J19/10,1)) | L19: =IF(K19="","",IF(K19>=9,"MB",IF(K19>=7.8,"B",IF(K19>=6,"S","NA"))))
A20: =IF(Alumnos!A8="","",Alumnos!A8) -> 4 | B20: =IF(Alumnos!B8="","",Alumnos!B8) | C20: =IF(Alumnos!D8="","",Alumnos!D8) | D20: =IF(Examenes!C8="","",Examenes!C8) | E20: =IF(Examenes!D8="","",Examenes!D8) | F20: =IF(Examenes!E8="","",Examenes!E8) | G20: =IFERROR(SUMIF(Entregables!$B$4:$B$18,$C20,Entregables!$I$4:$I$18)/(COUNTIFS(Entregables!$B$4:$B$18,$C20,Entregables!$I$4:$I$18,">0")*18)*100,"") | H20: =IF(Bitacora_IA!F8="","",Bitacora_IA!F8*10) | I20: =IFERROR(Asistencia!Y8*100,"") | J20: =IFERROR(IF(COUNT(D20:I20)=0,"",D20*$B$5+E20*$B$6+F20*$B$7+G20*$B$8+H20*$B$9+I20*$B$10),"") | K20: =IF(J20="","",ROUND(J20/10,1)) | L20: =IF(K20="","",IF(K20>=9,"MB",IF(K20>=7.8,"B",IF(K20>=6,"S","NA"))))
A21: =IF(Alumnos!A9="","",Alumnos!A9) -> 5 | B21: =IF(Alumnos!B9="","",Alumnos!B9) | C21: =IF(Alumnos!D9="","",Alumnos!D9) | D21: =IF(Examenes!C9="","",Examenes!C9) | E21: =IF(Examenes!D9="","",Examenes!D9) | F21: =IF(Examenes!E9="","",Examenes!E9) | G21: =IFERROR(SUMIF(Entregables!$B$4:$B$18,$C21,Entregables!$I$4:$I$18)/(COUNTIFS(Entregables!$B$4:$B$18,$C21,Entregables!$I$4:$I$18,">0")*18)*100,"") | H21: =IF(Bitacora_IA!F9="","",Bitacora_IA!F9*10) | I21: =IFERROR(Asistencia!Y9*100,"") | J21: =IFERROR(IF(COUNT(D21:I21)=0,"",D21*$B$5+E21*$B$6+F21*$B$7+G21*$B$8+H21*$B$9+I21*$B$10),"") | K21: =IF(J21="","",ROUND(J21/10,1)) | L21: =IF(K21="","",IF(K21>=9,"MB",IF(K21>=7.8,"B",IF(K21>=6,"S","NA"))))
A22: =IF(Alumnos!A10="","",Alumnos!A10) -> 6 | B22: =IF(Alumnos!B10="","",Alumnos!B10) | C22: =IF(Alumnos!D10="","",Alumnos!D10) | D22: =IF(Examenes!C10="","",Examenes!C10) | E22: =IF(Examenes!D10="","",Examenes!D10) | F22: =IF(Examenes!E10="","",Examenes!E10) | G22: =IFERROR(SUMIF(Entregables!$B$4:$B$18,$C22,Entregables!$I$4:$I$18)/(COUNTIFS(Entregables!$B$4:$B$18,$C22,Entregables!$I$4:$I$18,">0")*18)*100,"") | H22: =IF(Bitacora_IA!F10="","",Bitacora_IA!F10*10) | I22: =IFERROR(Asistencia!Y10*100,"") | J22: =IFERROR(IF(COUNT(D22:I22)=0,"",D22*$B$5+E22*$B$6+F22*$B$7+G22*$B$8+H22*$B$9+I22*$B$10),"") | K22: =IF(J22="","",ROUND(J22/10,1)) | L22: =IF(K22="","",IF(K22>=9,"MB",IF(K22>=7.8,"B",IF(K22>=6,"S","NA"))))
A23: =IF(Alumnos!A11="","",Alumnos!A11) -> 7 | B23: =IF(Alumnos!B11="","",Alumnos!B11) | C23: =IF(Alumnos!D11="","",Alumnos!D11) | D23: =IF(Examenes!C11="","",Examenes!C11) | E23: =IF(Examenes!D11="","",Examenes!D11) | F23: =IF(Examenes!E11="","",Examenes!E11) | G23: =IFERROR(SUMIF(Entregables!$B$4:$B$18,$C23,Entregables!$I$4:$I$18)/(COUNTIFS(Entregables!$B$4:$B$18,$C23,Entregables!$I$4:$I$18,">0")*18)*100,"") | H23: =IF(Bitacora_IA!F11="","",Bitacora_IA!F11*10) | I23: =IFERROR(Asistencia!Y11*100,"") | J23: =IFERROR(IF(COUNT(D23:I23)=0,"",D23*$B$5+E23*$B$6+F23*$B$7+G23*$B$8+H23*$B$9+I23*$B$10),"") | K23: =IF(J23="","",ROUND(J23/10,1)) | L23: =IF(K23="","",IF(K23>=9,"MB",IF(K23>=7.8,"B",IF(K23>=6,"S","NA"))))
A24: =IF(Alumnos!A12="","",Alumnos!A12) -> 8 | B24: =IF(Alumnos!B12="","",Alumnos!B12) | C24: =IF(Alumnos!D12="","",Alumnos!D12) | D24: =IF(Examenes!C12="","",Examenes!C12) | E24: =IF(Examenes!D12="","",Examenes!D12) | F24: =IF(Examenes!E12="","",Examenes!E12) | G24: =IFERROR(SUMIF(Entregables!$B$4:$B$18,$C24,Entregables!$I$4:$I$18)/(COUNTIFS(Entregables!$B$4:$B$18,$C24,Entregables!$I$4:$I$18,">0")*18)*100,"") | H24: =IF(Bitacora_IA!F12="","",Bitacora_IA!F12*10) | I24: =IFERROR(Asistencia!Y12*100,"") | J24: =IFERROR(IF(COUNT(D24:I24)=0,"",D24*$B$5+E24*$B$6+F24*$B$7+G24*$B$8+H24*$B$9+I24*$B$10),"") | K24: =IF(J24="","",ROUND(J24/10,1)) | L24: =IF(K24="","",IF(K24>=9,"MB",IF(K24>=7.8,"B",IF(K24>=6,"S","NA"))))
A25: =IF(Alumnos!A13="","",Alumnos!A13) -> 9 | B25: =IF(Alumnos!B13="","",Alumnos!B13) | C25: =IF(Alumnos!D13="","",Alumnos!D13) | D25: =IF(Examenes!C13="","",Examenes!C13) | E25: =IF(Examenes!D13="","",Examenes!D13) | F25: =IF(Examenes!E13="","",Examenes!E13) | G25: =IFERROR(SUMIF(Entregables!$B$4:$B$18,$C25,Entregables!$I$4:$I$18)/(COUNTIFS(Entregables!$B$4:$B$18,$C25,Entregables!$I$4:$I$18,">0")*18)*100,"") | H25: =IF(Bitacora_IA!F13="","",Bitacora_IA!F13*10) | I25: =IFERROR(Asistencia!Y13*100,"") | J25: =IFERROR(IF(COUNT(D25:I25)=0,"",D25*$B$5+E25*$B$6+F25*$B$7+G25*$B$8+H25*$B$9+I25*$B$10),"") | K25: =IF(J25="","",ROUND(J25/10,1)) | L25: =IF(K25="","",IF(K25>=9,"MB",IF(K25>=7.8,"B",IF(K25>=6,"S","NA"))))
A26: =IF(Alumnos!A14="","",Alumnos!A14) -> 10 | B26: =IF(Alumnos!B14="","",Alumnos!B14) | C26: =IF(Alumnos!D14="","",Alumnos!D14) | D26: =IF(Examenes!C14="","",Examenes!C14) | E26: =IF(Examenes!D14="","",Examenes!D14) | F26: =IF(Examenes!E14="","",Examenes!E14) | G26: =IFERROR(SUMIF(Entregables!$B$4:$B$18,$C26,Entregables!$I$4:$I$18)/(COUNTIFS(Entregables!$B$4:$B$18,$C26,Entregables!$I$4:$I$18,">0")*18)*100,"") | H26: =IF(Bitacora_IA!F14="","",Bitacora_IA!F14*10) | I26: =IFERROR(Asistencia!Y14*100,"") | J26: =IFERROR(IF(COUNT(D26:I26)=0,"",D26*$B$5+E26*$B$6+F26*$B$7+G26*$B$8+H26*$B$9+I26*$B$10),"") | K26: =IF(J26="","",ROUND(J26/10,1)) | L26: =IF(K26="","",IF(K26>=9,"MB",IF(K26>=7.8,"B",IF(K26>=6,"S","NA"))))
A27: =IF(Alumnos!A15="","",Alumnos!A15) -> 11 | B27: =IF(Alumnos!B15="","",Alumnos!B15) | C27: =IF(Alumnos!D15="","",Alumnos!D15) | D27: =IF(Examenes!C15="","",Examenes!C15) | E27: =IF(Examenes!D15="","",Examenes!D15) | F27: =IF(Examenes!E15="","",Examenes!E15) | G27: =IFERROR(SUMIF(Entregables!$B$4:$B$18,$C27,Entregables!$I$4:$I$18)/(COUNTIFS(Entregables!$B$4:$B$18,$C27,Entregables!$I$4:$I$18,">0")*18)*100,"") | H27: =IF(Bitacora_IA!F15="","",Bitacora_IA!F15*10) | I27: =IFERROR(Asistencia!Y15*100,"") | J27: =IFERROR(IF(COUNT(D27:I27)=0,"",D27*$B$5+E27*$B$6+F27*$B$7+G27*$B$8+H27*$B$9+I27*$B$10),"") | K27: =IF(J27="","",ROUND(J27/10,1)) | L27: =IF(K27="","",IF(K27>=9,"MB",IF(K27>=7.8,"B",IF(K27>=6,"S","NA"))))
... A41: =IF(Alumnos!A29="","",Alumnos!A29) -> 25 | B41: =IF(Alumnos!B29="","",Alumnos!B29) | C41: =IF(Alumnos!D29="","",Alumnos!D29) | D41: =IF(Examenes!C29="","",Examenes!C29) | E41: =IF(Examenes!D29="","",Examenes!D29) | F41: =IF(Examenes!E29="","",Examenes!E29) | G41: =IFERROR(SUMIF(Entregables!$B$4:$B$18,$C41,Entregables!$I$4:$I$18)/(COUNTIFS(Entregables!$B$4:$B$18,$C41,Entregables!$I$4:$I$18,">0")*18)*100,"") | H41: =IF(Bitacora_IA!F29="","",Bitacora_IA!F29*10) | I41: =IFERROR(Asistencia!Y29*100,"") | J41: =IFERROR(IF(COUNT(D41:I41)=0,"",D41*$B$5+E41*$B$6+F41*$B$7+G41*$B$8+H41*$B$9+I41*$B$10),"") | K41: =IF(J41="","",ROUND(J41/10,1)) | L41: =IF(K41="","",IF(K41>=9,"MB",IF(K41>=7.8,"B",IF(K41>=6,"S","NA"))))

Sheet Riesgo
A1: Semáforo de riesgo de deserción · revisar cada lunes
A2: ROJO = intervención inmediata (protocolo de 48 horas). ÁMBAR = vigilar. VERDE = sin señales. Umbrales ajustables en las celdas amarillas.
A4: Faltas para ÁMBAR | B4: 2
A5: Faltas para ROJO | B5: 4
A7: # | B7: Nombre | C7: ¿Contestó pre-curso? | D7: Punto de partida | E7: Faltas | F7: Entregas de bitácora faltantes | G7: Parcial (0-10) | H7: SEMÁFORO | I7: Acción tomada / fecha
A8: =IF(Alumnos!A4="","",Alumnos!A4) -> 1 | B8: =IF(Alumnos!B4="","",Alumnos!B4) -> EJEMPLO — borrar esta fila | C8: =IF(Alumnos!S4="","",Alumnos!S4) -> Sí | D8: =IF(Alumnos!R4="","",Alumnos!R4) -> Funcional | E8: =Asistencia!W4 -> 0 | F8: =3-COUNT(Bitacora_IA!C4:E4) -> 3 | G8: =IF(Calificaciones!K16="","",Calificaciones!K16) | H8: =IF(B8="","",IF(OR(E8>=$B$5,AND(C8="No",E8>=$B$4)),"ROJO",IF(OR(E8>=$B$4,D8="Elemental",C8="No"),"ÁMBAR","VERDE"))) -> VERDE
A9: =IF(Alumnos!A5="","",Alumnos!A5) -> 1 | B9: =IF(Alumnos!B5="","",Alumnos!B5) | C9: =IF(Alumnos!S5="","",Alumnos!S5) | D9: =IF(Alumnos!R5="","",Alumnos!R5) | E9: =Asistencia!W5 -> 0 | F9: =3-COUNT(Bitacora_IA!C5:E5) -> 3 | G9: =IF(Calificaciones!K17="","",Calificaciones!K17) | H9: =IF(B9="","",IF(OR(E9>=$B$5,AND(C9="No",E9>=$B$4)),"ROJO",IF(OR(E9>=$B$4,D9="Elemental",C9="No"),"ÁMBAR","VERDE")))
A10: =IF(Alumnos!A6="","",Alumnos!A6) -> 2 | B10: =IF(Alumnos!B6="","",Alumnos!B6) | C10: =IF(Alumnos!S6="","",Alumnos!S6) | D10: =IF(Alumnos!R6="","",Alumnos!R6) | E10: =Asistencia!W6 -> 0 | F10: =3-COUNT(Bitacora_IA!C6:E6) -> 3 | G10: =IF(Calificaciones!K18="","",Calificaciones!K18) | H10: =IF(B10="","",IF(OR(E10>=$B$5,AND(C10="No",E10>=$B$4)),"ROJO",IF(OR(E10>=$B$4,D10="Elemental",C10="No"),"ÁMBAR","VERDE")))
A11: =IF(Alumnos!A7="","",Alumnos!A7) -> 3 | B11: =IF(Alumnos!B7="","",Alumnos!B7) | C11: =IF(Alumnos!S7="","",Alumnos!S7) | D11: =IF(Alumnos!R7="","",Alumnos!R7) | E11: =Asistencia!W7 -> 0 | F11: =3-COUNT(Bitacora_IA!C7:E7) -> 3 | G11: =IF(Calificaciones!K19="","",Calificaciones!K19) | H11: =IF(B11="","",IF(OR(E11>=$B$5,AND(C11="No",E11>=$B$4)),"ROJO",IF(OR(E11>=$B$4,D11="Elemental",C11="No"),"ÁMBAR","VERDE")))
A12: =IF(Alumnos!A8="","",Alumnos!A8) -> 4 | B12: =IF(Alumnos!B8="","",Alumnos!B8) | C12: =IF(Alumnos!S8="","",Alumnos!S8) | D12: =IF(Alumnos!R8="","",Alumnos!R8) | E12: =Asistencia!W8 -> 0 | F12: =3-COUNT(Bitacora_IA!C8:E8) -> 3 | G12: =IF(Calificaciones!K20="","",Calificaciones!K20) | H12: =IF(B12="","",IF(OR(E12>=$B$5,AND(C12="No",E12>=$B$4)),"ROJO",IF(OR(E12>=$B$4,D12="Elemental",C12="No"),"ÁMBAR","VERDE")))
A13: =IF(Alumnos!A9="","",Alumnos!A9) -> 5 | B13: =IF(Alumnos!B9="","",Alumnos!B9) | C13: =IF(Alumnos!S9="","",Alumnos!S9) | D13: =IF(Alumnos!R9="","",Alumnos!R9) | E13: =Asistencia!W9 -> 0 | F13: =3-COUNT(Bitacora_IA!C9:E9) -> 3 | G13: =IF(Calificaciones!K21="","",Calificaciones!K21) | H13: =IF(B13="","",IF(OR(E13>=$B$5,AND(C13="No",E13>=$B$4)),"ROJO",IF(OR(E13>=$B$4,D13="Elemental",C13="No"),"ÁMBAR","VERDE")))
A14: =IF(Alumnos!A10="","",Alumnos!A10) -> 6 | B14: =IF(Alumnos!B10="","",Alumnos!B10) | C14: =IF(Alumnos!S10="","",Alumnos!S10) | D14: =IF(Alumnos!R10="","",Alumnos!R10) | E14: =Asistencia!W10 -> 0 | F14: =3-COUNT(Bitacora_IA!C10:E10) -> 3 | G14: =IF(Calificaciones!K22="","",Calificaciones!K22) | H14: =IF(B14="","",IF(OR(E14>=$B$5,AND(C14="No",E14>=$B$4)),"ROJO",IF(OR(E14>=$B$4,D14="Elemental",C14="No"),"ÁMBAR","VERDE")))
A15: =IF(Alumnos!A11="","",Alumnos!A11) -> 7 | B15: =IF(Alumnos!B11="","",Alumnos!B11) | C15: =IF(Alumnos!S11="","",Alumnos!S11) | D15: =IF(Alumnos!R11="","",Alumnos!R11) | E15: =Asistencia!W11 -> 0 | F15: =3-COUNT(Bitacora_IA!C11:E11) -> 3 | G15: =IF(Calificaciones!K23="","",Calificaciones!K23) | H15: =IF(B15="","",IF(OR(E15>=$B$5,AND(C15="No",E15>=$B$4)),"ROJO",IF(OR(E15>=$B$4,D15="Elemental",C15="No"),"ÁMBAR","VERDE")))
A16: =IF(Alumnos!A12="","",Alumnos!A12) -> 8 | B16: =IF(Alumnos!B12="","",Alumnos!B12) | C16: =IF(Alumnos!S12="","",Alumnos!S12) | D16: =IF(Alumnos!R12="","",Alumnos!R12) | E16: =Asistencia!W12 -> 0 | F16: =3-COUNT(Bitacora_IA!C12:E12) -> 3 | G16: =IF(Calificaciones!K24="","",Calificaciones!K24) | H16: =IF(B16="","",IF(OR(E16>=$B$5,AND(C16="No",E16>=$B$4)),"ROJO",IF(OR(E16>=$B$4,D16="Elemental",C16="No"),"ÁMBAR","VERDE")))
A17: =IF(Alumnos!A13="","",Alumnos!A13) -> 9 | B17: =IF(Alumnos!B13="","",Alumnos!B13) | C17: =IF(Alumnos!S13="","",Alumnos!S13) | D17: =IF(Alumnos!R13="","",Alumnos!R13) | E17: =Asistencia!W13 -> 0 | F17: =3-COUNT(Bitacora_IA!C13:E13) -> 3 | G17: =IF(Calificaciones!K25="","",Calificaciones!K25) | H17: =IF(B17="","",IF(OR(E17>=$B$5,AND(C17="No",E17>=$B$4)),"ROJO",IF(OR(E17>=$B$4,D17="Elemental",C17="No"),"ÁMBAR","VERDE")))
A18: =IF(Alumnos!A14="","",Alumnos!A14) -> 10 | B18: =IF(Alumnos!B14="","",Alumnos!B14) | C18: =IF(Alumnos!S14="","",Alumnos!S14) | D18: =IF(Alumnos!R14="","",Alumnos!R14) | E18: =Asistencia!W14 -> 0 | F18: =3-COUNT(Bitacora_IA!C14:E14) -> 3 | G18: =IF(Calificaciones!K26="","",Calificaciones!K26) | H18: =IF(B18="","",IF(OR(E18>=$B$5,AND(C18="No",E18>=$B$4)),"ROJO",IF(OR(E18>=$B$4,D18="Elemental",C18="No"),"ÁMBAR","VERDE")))
A19: =IF(Alumnos!A15="","",Alumnos!A15) -> 11 | B19: =IF(Alumnos!B15="","",Alumnos!B15) | C19: =IF(Alumnos!S15="","",Alumnos!S15) | D19: =IF(Alumnos!R15="","",Alumnos!R15) | E19: =Asistencia!W15 -> 0 | F19: =3-COUNT(Bitacora_IA!C15:E15) -> 3 | G19: =IF(Calificaciones!K27="","",Calificaciones!K27) | H19: =IF(B19="","",IF(OR(E19>=$B$5,AND(C19="No",E19>=$B$4)),"ROJO",IF(OR(E19>=$B$4,D19="Elemental",C19="No"),"ÁMBAR","VERDE")))
... A33: =IF(Alumnos!A29="","",Alumnos!A29) -> 25 | B33: =IF(Alumnos!B29="","",Alumnos!B29) | C33: =IF(Alumnos!S29="","",Alumnos!S29) | D33: =IF(Alumnos!R29="","",Alumnos!R29) | E33: =Asistencia!W29 -> 0 | F33: =3-COUNT(Bitacora_IA!C29:E29) -> 3 | G33: =IF(Calificaciones!K41="","",Calificaciones!K41) | H33: =IF(B33="","",IF(OR(E33>=$B$5,AND(C33="No",E33>=$B$4)),"ROJO",IF(OR(E33>=$B$4,D33="Elemental",C33="No"),"ÁMBAR","VERDE")))

Sheet Diario_docente
A1: Diario docente · se llena al terminar cada sesión, en cinco minutos
A2: Materia prima para evaluar el método y para cualquier publicación posterior. Los minutos reales por fase permiten comprobar si el microciclo se sostuvo o se comió una fase a las otras.
A3: Sesión | B3: Fecha | C3: Bloque | D3: Asistentes | E3: Min. activista | F3: Min. reflexiva | G3: Min. teórica | H3: Min. pragmática | I3: ¿Se cumplió el plan? | J3: Qué funcionó | K3: Qué falló | L3: Ajuste para la próxima
A4: S01 | B4: 21-sep | C4: Arranque
A5: S02 | B5: 23-sep | C5: P1 Activista
A6: S03 | B6: 28-sep | C6: P1 Reflexiva
A7: S04 | B7: 30-sep | C7: P1 Teórica
A8: S05 | B8: 05-oct | C8: P1 Teór→Prag
A9: S06 | B9: 07-oct | C9: Holgura 1
A10: S07 | B10: 14-oct | C10: P1 Pragmática
A11: S08 | B11: 19-oct | C11: P2 Activista
A12: S09 | B12: 21-oct | C12: P2 Reflexiva
A13: S10 | B13: 26-oct | C13: P2 Teórica
A14: S11 | B14: 28-oct | C14: P2 Teór→Prag
A15: S12 | B15: 04-nov | C15: P2 Pragmática
... A23: S20 | B23: 02-dic | C23: Holgura 4
A26: TOTALES | E26: =SUM(E4:E23) -> 0 | F26: =SUM(F4:F23) -> 0 | G26: =SUM(G4:G23) -> 0 | H26: =SUM(H4:H23) -> 0
A27: % del tiempo por fase | E27: =IFERROR(E26/SUM($E$26:$H$26),"") | F27: =IFERROR(F26/SUM($E$26:$H$26),"") | G27: =IFERROR(G26/SUM($E$26:$H$26),"") | H27: =IFERROR(H26/SUM($E$26:$H$26),"")
A28: Si una fase se lleva menos del 15% del tiempo total, el equilibrio entre estilos no se cumplió.

Sheet Evaluacion_metodo
A1: Evaluación del método · cierre del trimestre
A3: 1. INDICADORES DUROS
A4: Inscritos al inicio | B4: 25 | D4: Dato de acta
A5: Alumnos que concluyeron | D5: Capturar al cierre
A6: Tasa de retención | B6: =IFERROR(B5/B4,"") -> 0 | D6: Meta: superar el promedio histórico del grupo
A7: Aprobados | D7: Capturar al cierre
A8: Tasa de aprobación sobre inscritos | B8: =IFERROR(B7/B4,"") -> 0
A9: Promedio del grupo (0-10) | B9: =IFERROR(AVERAGE(Calificaciones!K16:K41),"") | D9: Calculado
A10: Diagnóstico inicial promedio (0-17) | B10: =IFERROR(AVERAGE(Alumnos!Q4:Q29),"") -> 9 | D10: Calculado
A11: Diagnóstico final promedio (0-17) | D11: Aplicar el MISMO instrumento en la sesión 20
A12: Ganancia de aprendizaje | B12: =IFERROR(B11-B10,"") -> -9 | D12: La medida más limpia del efecto del método
A15: 2. PREGUNTAS DE VALORACIÓN DOCENTE
A16: ¿El proyecto 1 fue realizable en cinco sesiones o hubo que usar holgura?
A17: ¿En qué sesión concreta se perdió a cada alumno que desertó? ¿Qué señal hubo antes?
A18: ¿La fase activista produjo el enganche esperado, o los alumnos pidieron que se les explicara primero?
A19: ¿El laboratorio simulado funcionó, o el chatbot resultó demasiado poco confiable para sostenerlo?
A20: ¿Los alumnos detectaron errores del chatbot por sí solos, o hubo que señalárselos?
A21: ¿La rotación de roles se cumplió o los equipos volvieron al reparto cómodo?
A22: ¿Los exámenes sobre el propio proyecto discriminaron bien entre quien trabajó y quien no?
A23: ¿La distribución de estilos CHAEA se correlacionó con algo observable en el desempeño?
A24: ¿Qué proyecto habría que rediseñar antes de 27-I y por qué?
A25: ¿La carga de trabajo del profesor fue sostenible? ¿Qué parte del seguimiento se abandonó primero?
A28: 3. CRUCE ESTILO CHAEA × DESEMPEÑO
A29: Estilo dominante | B29: N | C29: Promedio final | D29: Notas
A30: Activo | B30: =COUNTIF(Alumnos!$P$4:$P$29,A30) -> 1 | C30: =IFERROR(SUMIF(Alumnos!$P$4:$P$29,A30,Calificaciones!$K$16:$K$41)/B30,"") -> 0
A31: Reflexivo | B31: =COUNTIF(Alumnos!$P$4:$P$29,A31) -> 0 | C31: =IFERROR(SUMIF(Alumnos!$P$4:$P$29,A31,Calificaciones!$K$16:$K$41)/B31,"")
A32: Teórico | B32: =COUNTIF(Alumnos!$P$4:$P$29,A32) -> 0 | C32: =IFERROR(SUMIF(Alumnos!$P$4:$P$29,A32,Calificaciones!$K$16:$K$41)/B32,"")
A33: Pragmático | B33: =COUNTIF(Alumnos!$P$4:$P$29,A33) -> 0 | C33: =IFERROR(SUMIF(Alumnos!$P$4:$P$29,A33,Calificaciones!$K$16:$K$41)/B33,"")
A35: Con 25 casos no hay potencia estadística: esto es exploratorio. Acumulando trimestres sí la hay, y la pregunta —si el diseño equilibrado por estilos reduce la deserción en primer trimestre— es una pregunta abierta y publicable. Conviene guardar estos datos anonimizados cada trimestre.
